ninfo/__init__.py
ninfo/util.py
ninfo/helpers/__init__.py
ninfo/helpers/splunk.py
ninfo-1.0.1.dist-info/LICENSE
ninfo-1.0.1.dist-info/METADATA
ninfo-1.0.1.dist-info/WHEEL
ninfo-1.0.1.dist-info/entry_points.txt
ninfo-1.0.1.dist-info/top_level.txt
ninfo-1.0.1.dist-info/RECORD
