Metadata-Version: 2.1
Name: ninfo
Version: 1.0.1
Summary: Plugin based information gathering library
Author-email: Justin Azoff <justin.azoff@gmail.com>, Ryan Goggin <support@ryangoggin.net>
Project-URL: Homepage, https://github.com/ninfo-py/ninfo
Keywords: ninfo,search
Classifier: License :: OSI Approved :: MIT License
Classifier: Programming Language :: Python
Classifier: Programming Language :: Python :: 2
Classifier: Programming Language :: Python :: 3
Requires-Python: >=2.7
License-File: LICENSE
Requires-Dist: Mako
Requires-Dist: python-memcached
Requires-Dist: ieeemac
Requires-Dist: IPy
Provides-Extra: splunk
Requires-Dist: splunk-sdk ; extra == 'splunk'
Provides-Extra: dev
Requires-Dist: black ; extra == 'dev'
Requires-Dist: bumpver ; extra == 'dev'
Requires-Dist: isort ; extra == 'dev'
Requires-Dist: pip-tools ; extra == 'dev'
Requires-Dist: pytest ; extra == 'dev'
